setup.py
distributionsVeer/Binomialdistribution.py
distributionsVeer/Gaussiandistribution.py
distributionsVeer/Generaldistribution.py
distributionsVeer/__init__.py
distributionsVeer.egg-info/PKG-INFO
distributionsVeer.egg-info/SOURCES.txt
distributionsVeer.egg-info/dependency_links.txt
distributionsVeer.egg-info/not-zip-safe
distributionsVeer.egg-info/top_level.txt