Metadata-Version: 1.0
Name: distributionsVeer
Version: 0.1
Summary: Gaussian and Binomial distributions
Home-page: UNKNOWN
Author: Veeru Talreja
Author-email: UNKNOWN
License: UNKNOWN
Platform: UNKNOWN
